acc_sdk/__init__.py
acc_sdk/acc.py
acc_sdk/account_users.py
acc_sdk/authentication.py
acc_sdk/base.py
acc_sdk/business_units.py
acc_sdk/companies.py
acc_sdk/data_connector.py
acc_sdk/data_management.py
acc_sdk/forms.py
acc_sdk/photos.py
acc_sdk/project_users.py
acc_sdk/projects.py
acc_sdk/sheets.py
acc_sdk/userprofile.py
docs/__init__.py
docs/account_users_api.md
docs/authentication.md
docs/business_units_api.md
docs/companies_api.md
docs/data_connector_api.md
docs/forms_api.md
docs/photos_api.md
docs/project_users_api.md
docs/projects_api.md
docs/sheets_api.md
docs/user_profile_api.md
acc_sdk-0.5.10.dist-info/METADATA
acc_sdk-0.5.10.dist-info/WHEEL
acc_sdk-0.5.10.dist-info/entry_points.txt
acc_sdk-0.5.10.dist-info/RECORD
