Metadata-Version: 2.3
Name: acc_sdk
Version: 0.5.10
Summary: An Unofficial Python Implementation of the Autodesk Construction Cloud API SDK
License: MIT
Author: Daniel Byrne
Author-email: realdanielbyrne@icloud.com
Maintainer: Daniel Byrne
Maintainer-email: realdanielbyrne@icloud.com
Requires-Python: >= 3.12
Classifier: License :: OSI Approved :: MIT License
Classifier: Programming Language :: Python :: 3
Classifier: Programming Language :: Python :: 3.12
Classifier: Programming Language :: Python :: 3.13
Requires-Dist: argparse (>=1.4.0,<2.0.0)
Requires-Dist: black (>=25.1.0,<26.0.0)
Requires-Dist: flask (>=3.1.0,<4.0.0)
Requires-Dist: ipython (>=9.0.1,<10.0.0)
Requires-Dist: python-dotenv (>=1.0.1,<2.0.0)
Requires-Dist: requests (>=2.32.3,<3.0.0)
Requires-Dist: ruff (>=0.11.2,<0.12.0)
Project-URL: Repository, https://github.com/realdanielbyrne/acc_sdk
